ffre/__init__.py
ffre/core.py
ffre-0.1.0.dist-info/METADATA
ffre-0.1.0.dist-info/WHEEL
ffre-0.1.0.dist-info/top_level.txt
ffre-0.1.0.dist-info/RECORD
